{
    "video_name": "195_first_person.mp4",
    "clips": [
        {
            "clip_id": "195_0",
            "action_time": [
                0,
                1.265
            ],
            "action_label": {
                "id_action": "001",
                "description": "Press the two green buttons on panel A"
            }
        },
        {
            "clip_id": "195_1",
            "action_time": [
                1.265,
                7.066
            ],
            "action_label": {
                "id_action": "002",
                "description": "Moves to the workbench and sits down"
            }
        },
        {
            "clip_id": "195_2",
            "action_time": [
                15.859,
                18.587
            ],
            "action_label": {
                "id_action": "055",
                "description": "Takes the low-voltage card"
            }
        },
        {
            "clip_id": "195_3",
            "action_time": [
                18.578,
                20.238
            ],
            "action_label": {
                "id_action": "004",
                "description": "Places the card on the work area"
            }
        },
        {
            "clip_id": "195_4",
            "action_time": [
                21.89,
                31.735
            ],
            "action_label": {
                "id_action": "005",
                "description": "Connects the battery to the screwdriver"
            }
        },
        {
            "clip_id": "195_5",
            "action_time": [
                31.739,
                43.203
            ],
            "action_label": {
                "id_action": "006",
                "description": "Removes the workbench screws using the screwdriver"
            }
        },
        {
            "clip_id": "195_6",
            "action_time": [
                47.718,
                84.614
            ],
            "action_label": {
                "id_action": "007",
                "description": "Fixes the card to the workbench using the screwdriver"
            }
        },
        {
            "clip_id": "195_7",
            "action_time": [
                89.334,
                93.265
            ],
            "action_label": {
                "id_action": "045",
                "description": "Disconnects the screwdriver battery and connects it to the battery charger"
            }
        },
        {
            "clip_id": "195_8",
            "action_time": [
                93.272,
                97.843
            ],
            "action_label": {
                "id_action": "045",
                "description": "Disconnects the screwdriver battery and connects it to the battery charger"
            }
        },
        {
            "clip_id": "195_9",
            "action_time": [
                97.853,
                100.458
            ],
            "action_label": {
                "id_action": "046",
                "description": "Turns on the screwdriver battery charger via the tower switch"
            }
        },
        {
            "clip_id": "195_10",
            "action_time": [
                115.781,
                116.828
            ],
            "action_label": {
                "id_action": "008",
                "description": "Turns on the power supply via the tower switch"
            }
        },
        {
            "clip_id": "195_11",
            "action_time": [
                119.578,
                122.797
            ],
            "action_label": {
                "id_action": "009",
                "description": "Adjusts the power supply current knob until the green LED turns on"
            }
        },
        {
            "clip_id": "195_12",
            "action_time": [
                122.797,
                135.441
            ],
            "action_label": {
                "id_action": "010",
                "description": "Adjusts the power supply voltage knob setting it to 5 Volts"
            }
        },
        {
            "clip_id": "195_13",
            "action_time": [
                135.437,
                159.031
            ],
            "action_label": {
                "id_action": "011",
                "description": "Connects the power supply cables to the card's power points"
            }
        },
        {
            "clip_id": "195_14",
            "action_time": [
                165.672,
                167.64
            ],
            "action_label": {
                "id_action": "030",
                "description": "Turns on the oscilloscope via the tower switch"
            }
        },
        {
            "clip_id": "195_15",
            "action_time": [
                167.64,
                175.718
            ],
            "action_label": {
                "id_action": "031",
                "description": "Activates the probe channel number 2 using the blue-bordered CH2 MENU button"
            }
        },
        {
            "clip_id": "195_16",
            "action_time": [
                184.484,
                189.759
            ],
            "action_label": {
                "id_action": "032",
                "description": "Connects the probe ground clip to test point number 1"
            }
        },
        {
            "clip_id": "195_17",
            "action_time": [
                204.25,
                211.984
            ],
            "action_label": {
                "id_action": "033",
                "description": "Uses the probe tip to check some signal brought to test point number 2 on the card"
            }
        },
        {
            "clip_id": "195_18",
            "action_time": [
                211.984,
                214.625
            ],
            "action_label": {
                "id_action": "034",
                "description": "Presses the oscilloscope's Auto Set button"
            }
        },
        {
            "clip_id": "195_19",
            "action_time": [
                227.734,
                231.187
            ],
            "action_label": {
                "id_action": "036",
                "description": "Uses the probe tip at test point number 3 on the card"
            }
        },
        {
            "clip_id": "195_20",
            "action_time": [
                231.187,
                233.187
            ],
            "action_label": {
                "id_action": "034",
                "description": "Presses the oscilloscope's Auto Set button"
            }
        },
        {
            "clip_id": "195_21",
            "action_time": [
                255.515,
                259.453
            ],
            "action_label": {
                "id_action": "037",
                "description": "Uses the probe tip at test point number 4 on the card"
            }
        },
        {
            "clip_id": "195_22",
            "action_time": [
                259.453,
                261.031
            ],
            "action_label": {
                "id_action": "034",
                "description": "Presses the oscilloscope's Auto Set button"
            }
        },
        {
            "clip_id": "195_23",
            "action_time": [
                274.752,
                277.031
            ],
            "action_label": {
                "id_action": "034",
                "description": "Presses the oscilloscope's Auto Set button"
            }
        },
        {
            "clip_id": "195_24",
            "action_time": [
                293.39,
                294.861
            ],
            "action_label": {
                "id_action": "034",
                "description": "Presses the oscilloscope's Auto Set button"
            }
        },
        {
            "clip_id": "195_25",
            "action_time": [
                306.047,
                312.468
            ],
            "action_label": {
                "id_action": "039",
                "description": "Uses the probe tip at test point number 7 on the card"
            }
        },
        {
            "clip_id": "195_26",
            "action_time": [
                312.468,
                314.5
            ],
            "action_label": {
                "id_action": "034",
                "description": "Presses the oscilloscope's Auto Set button"
            }
        },
        {
            "clip_id": "195_27",
            "action_time": [
                330.328,
                331.187
            ],
            "action_label": {
                "id_action": "012",
                "description": "Turns off the card's power supply via the tower switch"
            }
        },
        {
            "clip_id": "195_28",
            "action_time": [
                331.187,
                335.765
            ],
            "action_label": {
                "id_action": "013",
                "description": "Resets the power supply current and voltage knobs to 0"
            }
        },
        {
            "clip_id": "195_29",
            "action_time": [
                338.39,
                342.832
            ],
            "action_label": {
                "id_action": "040",
                "description": "Disconnects the ground clip and oscilloscope probe"
            }
        },
        {
            "clip_id": "195_30",
            "action_time": [
                342.832,
                347.216
            ],
            "action_label": {
                "id_action": "014",
                "description": "Disconnects the power supply cables"
            }
        },
        {
            "clip_id": "195_31",
            "action_time": [
                354.984,
                356.14
            ],
            "action_label": {
                "id_action": "041",
                "description": "Deactivates the probe channel number 2"
            }
        },
        {
            "clip_id": "195_32",
            "action_time": [
                356.14,
                358.922
            ],
            "action_label": {
                "id_action": "042",
                "description": "Turns off the oscilloscope via the tower switch"
            }
        },
        {
            "clip_id": "195_33",
            "action_time": [
                371.922,
                373.209
            ],
            "action_label": {
                "id_action": "050",
                "description": "Turns off the screwdriver battery charger via the tower switch"
            }
        },
        {
            "clip_id": "195_34",
            "action_time": [
                373.209,
                378.14
            ],
            "action_label": {
                "id_action": "005",
                "description": "Connects the battery to the screwdriver"
            }
        },
        {
            "clip_id": "195_35",
            "action_time": [
                381.422,
                407.718
            ],
            "action_label": {
                "id_action": "015",
                "description": "Removes the card from the workbench using the screwdriver"
            }
        },
        {
            "clip_id": "195_36",
            "action_time": [
                415.609,
                435.093
            ],
            "action_label": {
                "id_action": "044",
                "description": "Reinserts the screws in the work area using the screwdriver"
            }
        },
        {
            "clip_id": "195_37",
            "action_time": [
                441.031,
                447.102
            ],
            "action_label": {
                "id_action": "045",
                "description": "Disconnects the screwdriver battery and connects it to the battery charger"
            }
        },
        {
            "clip_id": "195_38",
            "action_time": [
                447.102,
                449.078
            ],
            "action_label": {
                "id_action": "045",
                "description": "Disconnects the screwdriver battery and connects it to the battery charger"
            }
        },
        {
            "clip_id": "195_39",
            "action_time": [
                449.078,
                450.707
            ],
            "action_label": {
                "id_action": "046",
                "description": "Turns on the screwdriver battery charger via the tower switch"
            }
        },
        {
            "clip_id": "195_40",
            "action_time": [
                454.734,
                485.973
            ],
            "action_label": {
                "id_action": "047",
                "description": "Notes the test operation results in the register"
            }
        },
        {
            "clip_id": "195_41",
            "action_time": [
                496.937,
                497.64
            ],
            "action_label": {
                "id_action": "048",
                "description": "Presses the two red buttons on panel A"
            }
        }
    ]
}