{
    "video_name": "81_first_person.mp4",
    "clips": [
        {
            "clip_id": "81_0",
            "action_time": [
                0,
                2.61
            ],
            "action_label": {
                "id_action": "001",
                "description": "Press the two green buttons on panel A"
            }
        },
        {
            "clip_id": "81_1",
            "action_time": [
                2.61,
                10.236
            ],
            "action_label": {
                "id_action": "002",
                "description": "Moves to the workbench and sits down"
            }
        },
        {
            "clip_id": "81_2",
            "action_time": [
                15.469,
                20.891
            ],
            "action_label": {
                "id_action": "003",
                "description": "Takes the high-voltage card"
            }
        },
        {
            "clip_id": "81_3",
            "action_time": [
                20.891,
                22.657
            ],
            "action_label": {
                "id_action": "004",
                "description": "Places the card on the work area"
            }
        },
        {
            "clip_id": "81_4",
            "action_time": [
                32.25,
                45.25
            ],
            "action_label": {
                "id_action": "005",
                "description": "Connects the battery to the screwdriver"
            }
        },
        {
            "clip_id": "81_5",
            "action_time": [
                45.25,
                58.75
            ],
            "action_label": {
                "id_action": "006",
                "description": "Removes the workbench screws using the screwdriver"
            }
        },
        {
            "clip_id": "81_6",
            "action_time": [
                63.422,
                109.951
            ],
            "action_label": {
                "id_action": "007",
                "description": "Fixes the card to the workbench using the screwdriver"
            }
        },
        {
            "clip_id": "81_7",
            "action_time": [
                120.875,
                122.938
            ],
            "action_label": {
                "id_action": "008",
                "description": "Turns on the power supply via the tower switch"
            }
        },
        {
            "clip_id": "81_8",
            "action_time": [
                129.688,
                135.594
            ],
            "action_label": {
                "id_action": "009",
                "description": "Adjusts the power supply current knob until the green LED turns on"
            }
        },
        {
            "clip_id": "81_9",
            "action_time": [
                135.606,
                148.985
            ],
            "action_label": {
                "id_action": "010",
                "description": "Adjusts the power supply voltage knob setting it to 5 Volts"
            }
        },
        {
            "clip_id": "81_10",
            "action_time": [
                153.157,
                171.313
            ],
            "action_label": {
                "id_action": "011",
                "description": "Connects the power supply cables to the card's power points"
            }
        },
        {
            "clip_id": "81_11",
            "action_time": [
                181.969,
                184.563
            ],
            "action_label": {
                "id_action": "012",
                "description": "Turns off the card's power supply via the tower switch"
            }
        },
        {
            "clip_id": "81_12",
            "action_time": [
                184.565,
                193.922
            ],
            "action_label": {
                "id_action": "013",
                "description": "Resets the power supply current and voltage knobs to 0"
            }
        },
        {
            "clip_id": "81_13",
            "action_time": [
                197.563,
                203.547
            ],
            "action_label": {
                "id_action": "014",
                "description": "Disconnects the power supply cables"
            }
        },
        {
            "clip_id": "81_14",
            "action_time": [
                203.547,
                221.485
            ],
            "action_label": {
                "id_action": "015",
                "description": "Removes the card from the workbench using the screwdriver"
            }
        },
        {
            "clip_id": "81_15",
            "action_time": [
                232.25,
                234.579
            ],
            "action_label": {
                "id_action": "016",
                "description": "Turns on the soldering iron via the tower switch"
            }
        },
        {
            "clip_id": "81_16",
            "action_time": [
                234.579,
                252.0
            ],
            "action_label": {
                "id_action": "017",
                "description": "Sets the soldering iron temperature to 200 degrees using the yellow UP button"
            }
        },
        {
            "clip_id": "81_17",
            "action_time": [
                264.063,
                267.158
            ],
            "action_label": {
                "id_action": "056",
                "description": "Grasps the resistor on the card with pliers"
            }
        },
        {
            "clip_id": "81_18",
            "action_time": [
                272.204,
                277.332
            ],
            "action_label": {
                "id_action": "019",
                "description": "Takes the soldering iron tip"
            }
        },
        {
            "clip_id": "81_19",
            "action_time": [
                277.338,
                287.329
            ],
            "action_label": {
                "id_action": "057",
                "description": "Touches the first pin of the resistor with the tip"
            }
        },
        {
            "clip_id": "81_20",
            "action_time": [
                290.954,
                297.313
            ],
            "action_label": {
                "id_action": "021",
                "description": "Touches the second pin of the capacitor with the tip"
            }
        },
        {
            "clip_id": "81_21",
            "action_time": [
                298.157,
                299.579
            ],
            "action_label": {
                "id_action": "022",
                "description": "Places the pliers on the workbench"
            }
        },
        {
            "clip_id": "81_22",
            "action_time": [
                299.579,
                303.375
            ],
            "action_label": {
                "id_action": "023",
                "description": "Places the soldering iron tip"
            }
        },
        {
            "clip_id": "81_23",
            "action_time": [
                314.157,
                316.0
            ],
            "action_label": {
                "id_action": "024",
                "description": "Puts the card vertically"
            }
        },
        {
            "clip_id": "81_24",
            "action_time": [
                316.0,
                318.765
            ],
            "action_label": {
                "id_action": "056",
                "description": "Grasps the resistor on the card with pliers"
            }
        },
        {
            "clip_id": "81_25",
            "action_time": [
                323.485,
                332.375
            ],
            "action_label": {
                "id_action": "019",
                "description": "Takes the soldering iron tip"
            }
        },
        {
            "clip_id": "81_26",
            "action_time": [
                332.375,
                340.579
            ],
            "action_label": {
                "id_action": "025",
                "description": "Touches the first pin of the capacitor on the back of the card with the tip"
            }
        },
        {
            "clip_id": "81_27",
            "action_time": [
                342.704,
                349.891
            ],
            "action_label": {
                "id_action": "060",
                "description": "Touches the second pin of the resistor on the back of the card with the tip"
            }
        },
        {
            "clip_id": "81_28",
            "action_time": [
                349.891,
                353.602
            ],
            "action_label": {
                "id_action": "023",
                "description": "Places the soldering iron tip"
            }
        },
        {
            "clip_id": "81_29",
            "action_time": [
                353.602,
                357.563
            ],
            "action_label": {
                "id_action": "004",
                "description": "Places the card on the work area"
            }
        },
        {
            "clip_id": "81_30",
            "action_time": [
                355.25,
                356.25
            ],
            "action_label": {
                "id_action": "022",
                "description": "Places the pliers on the workbench"
            }
        },
        {
            "clip_id": "81_31",
            "action_time": [
                365.204,
                381.407
            ],
            "action_label": {
                "id_action": "028",
                "description": "Reduces the soldering iron temperature to minimum (160 degrees) using the yellow DOWN button"
            }
        },
        {
            "clip_id": "81_32",
            "action_time": [
                381.407,
                386.157
            ],
            "action_label": {
                "id_action": "029",
                "description": "Turns off the soldering iron via the tower switch"
            }
        },
        {
            "clip_id": "81_33",
            "action_time": [
                392.0,
                465.235
            ],
            "action_label": {
                "id_action": "007",
                "description": "Fixes the card to the workbench using the screwdriver"
            }
        },
        {
            "clip_id": "81_34",
            "action_time": [
                473.938,
                476.36
            ],
            "action_label": {
                "id_action": "008",
                "description": "Turns on the power supply via the tower switch"
            }
        },
        {
            "clip_id": "81_35",
            "action_time": [
                481.813,
                486.141
            ],
            "action_label": {
                "id_action": "009",
                "description": "Adjusts the power supply current knob until the green LED turns on"
            }
        },
        {
            "clip_id": "81_36",
            "action_time": [
                486.141,
                498.532
            ],
            "action_label": {
                "id_action": "010",
                "description": "Adjusts the power supply voltage knob setting it to 5 Volts"
            }
        },
        {
            "clip_id": "81_37",
            "action_time": [
                503.704,
                518.79
            ],
            "action_label": {
                "id_action": "011",
                "description": "Connects the power supply cables to the card's power points"
            }
        },
        {
            "clip_id": "81_38",
            "action_time": [
                525.375,
                538.563
            ],
            "action_label": {
                "id_action": "030",
                "description": "Turns on the oscilloscope via the tower switch"
            }
        },
        {
            "clip_id": "81_39",
            "action_time": [
                538.563,
                543.469
            ],
            "action_label": {
                "id_action": "031",
                "description": "Activates the probe channel number 2 using the blue-bordered CH2 MENU button"
            }
        },
        {
            "clip_id": "81_40",
            "action_time": [
                559.172,
                563.201
            ],
            "action_label": {
                "id_action": "032",
                "description": "Connects the probe ground clip to test point number 1"
            }
        },
        {
            "clip_id": "81_41",
            "action_time": [
                573.625,
                588.313
            ],
            "action_label": {
                "id_action": "033",
                "description": "Uses the probe tip to check some signal brought to test point number 2 on the card"
            }
        },
        {
            "clip_id": "81_42",
            "action_time": [
                588.313,
                591.357
            ],
            "action_label": {
                "id_action": "034",
                "description": "Presses the oscilloscope's Auto Set button"
            }
        },
        {
            "clip_id": "81_43",
            "action_time": [
                607.407,
                615.61
            ],
            "action_label": {
                "id_action": "035",
                "description": "Randomly rotates the position knob"
            }
        },
        {
            "clip_id": "81_44",
            "action_time": [
                626.907,
                629.407
            ],
            "action_label": {
                "id_action": "036",
                "description": "Uses the probe tip at test point number 3 on the card"
            }
        },
        {
            "clip_id": "81_45",
            "action_time": [
                629.407,
                632.125
            ],
            "action_label": {
                "id_action": "034",
                "description": "Presses the oscilloscope's Auto Set button"
            }
        },
        {
            "clip_id": "81_46",
            "action_time": [
                640.907,
                646.5
            ],
            "action_label": {
                "id_action": "035",
                "description": "Randomly rotates the position knob"
            }
        },
        {
            "clip_id": "81_47",
            "action_time": [
                661.438,
                663.516
            ],
            "action_label": {
                "id_action": "034",
                "description": "Presses the oscilloscope's Auto Set button"
            }
        },
        {
            "clip_id": "81_48",
            "action_time": [
                674.625,
                679.032
            ],
            "action_label": {
                "id_action": "035",
                "description": "Randomly rotates the position knob"
            }
        },
        {
            "clip_id": "81_49",
            "action_time": [
                691.5,
                713.485
            ],
            "action_label": {
                "id_action": "038",
                "description": "Uses the probe tip at test point number 5 on the card"
            }
        },
        {
            "clip_id": "81_50",
            "action_time": [
                692.891,
                695.625
            ],
            "action_label": {
                "id_action": "034",
                "description": "Presses the oscilloscope's Auto Set button"
            }
        },
        {
            "clip_id": "81_51",
            "action_time": [
                704.5,
                709.547
            ],
            "action_label": {
                "id_action": "035",
                "description": "Randomly rotates the position knob"
            }
        },
        {
            "clip_id": "81_52",
            "action_time": [
                722.344,
                724.563
            ],
            "action_label": {
                "id_action": "034",
                "description": "Presses the oscilloscope's Auto Set button"
            }
        },
        {
            "clip_id": "81_53",
            "action_time": [
                736.297,
                740.657
            ],
            "action_label": {
                "id_action": "035",
                "description": "Randomly rotates the position knob"
            }
        },
        {
            "clip_id": "81_54",
            "action_time": [
                749.157,
                752.657
            ],
            "action_label": {
                "id_action": "012",
                "description": "Turns off the card's power supply via the tower switch"
            }
        },
        {
            "clip_id": "81_55",
            "action_time": [
                752.666,
                761.813
            ],
            "action_label": {
                "id_action": "013",
                "description": "Resets the power supply current and voltage knobs to 0"
            }
        },
        {
            "clip_id": "81_56",
            "action_time": [
                766.782,
                775.75
            ],
            "action_label": {
                "id_action": "040",
                "description": "Disconnects the ground clip and oscilloscope probe"
            }
        },
        {
            "clip_id": "81_57",
            "action_time": [
                775.752,
                780.625
            ],
            "action_label": {
                "id_action": "014",
                "description": "Disconnects the power supply cables"
            }
        },
        {
            "clip_id": "81_58",
            "action_time": [
                796.063,
                799.75
            ],
            "action_label": {
                "id_action": "041",
                "description": "Deactivates the probe channel number 2"
            }
        },
        {
            "clip_id": "81_59",
            "action_time": [
                799.75,
                804.344
            ],
            "action_label": {
                "id_action": "042",
                "description": "Turns off the oscilloscope via the tower switch"
            }
        },
        {
            "clip_id": "81_60",
            "action_time": [
                809.641,
                830.704
            ],
            "action_label": {
                "id_action": "015",
                "description": "Removes the card from the workbench using the screwdriver"
            }
        },
        {
            "clip_id": "81_61",
            "action_time": [
                844.422,
                847.879
            ],
            "action_label": {
                "id_action": "016",
                "description": "Turns on the soldering iron via the tower switch"
            }
        },
        {
            "clip_id": "81_62",
            "action_time": [
                847.876,
                867.75
            ],
            "action_label": {
                "id_action": "017",
                "description": "Sets the soldering iron temperature to 200 degrees using the yellow UP button"
            }
        },
        {
            "clip_id": "81_63",
            "action_time": [
                877.016,
                882.66
            ],
            "action_label": {
                "id_action": "056",
                "description": "Grasps the resistor on the card with pliers"
            }
        },
        {
            "clip_id": "81_64",
            "action_time": [
                887.5,
                892.532
            ],
            "action_label": {
                "id_action": "019",
                "description": "Takes the soldering iron tip"
            }
        },
        {
            "clip_id": "81_65",
            "action_time": [
                892.532,
                902.719
            ],
            "action_label": {
                "id_action": "057",
                "description": "Touches the first pin of the resistor with the tip"
            }
        },
        {
            "clip_id": "81_66",
            "action_time": [
                902.719,
                914.5
            ],
            "action_label": {
                "id_action": "058",
                "description": "Touches the second pin of the resistor with the tip"
            }
        },
        {
            "clip_id": "81_67",
            "action_time": [
                916.063,
                918.219
            ],
            "action_label": {
                "id_action": "022",
                "description": "Places the pliers on the workbench"
            }
        },
        {
            "clip_id": "81_68",
            "action_time": [
                918.219,
                921.719
            ],
            "action_label": {
                "id_action": "023",
                "description": "Places the soldering iron tip"
            }
        },
        {
            "clip_id": "81_69",
            "action_time": [
                929.5,
                936.844
            ],
            "action_label": {
                "id_action": "024",
                "description": "Puts the card vertically"
            }
        },
        {
            "clip_id": "81_70",
            "action_time": [
                934.141,
                938.927
            ],
            "action_label": {
                "id_action": "056",
                "description": "Grasps the resistor on the card with pliers"
            }
        },
        {
            "clip_id": "81_71",
            "action_time": [
                942.32,
                949.625
            ],
            "action_label": {
                "id_action": "019",
                "description": "Takes the soldering iron tip"
            }
        },
        {
            "clip_id": "81_72",
            "action_time": [
                949.625,
                959.016
            ],
            "action_label": {
                "id_action": "059",
                "description": "Touches the first pin of the resistor on the back of the card with the tip"
            }
        },
        {
            "clip_id": "81_73",
            "action_time": [
                959.016,
                971.954
            ],
            "action_label": {
                "id_action": "060",
                "description": "Touches the second pin of the resistor on the back of the card with the tip"
            }
        },
        {
            "clip_id": "81_74",
            "action_time": [
                971.954,
                974.797
            ],
            "action_label": {
                "id_action": "023",
                "description": "Places the soldering iron tip"
            }
        },
        {
            "clip_id": "81_75",
            "action_time": [
                974.797,
                978.5
            ],
            "action_label": {
                "id_action": "004",
                "description": "Places the card on the work area"
            }
        },
        {
            "clip_id": "81_76",
            "action_time": [
                977.745,
                978.297
            ],
            "action_label": {
                "id_action": "022",
                "description": "Places the pliers on the workbench"
            }
        },
        {
            "clip_id": "81_77",
            "action_time": [
                985.375,
                998.835
            ],
            "action_label": {
                "id_action": "028",
                "description": "Reduces the soldering iron temperature to minimum (160 degrees) using the yellow DOWN button"
            }
        },
        {
            "clip_id": "81_78",
            "action_time": [
                998.835,
                1001.789
            ],
            "action_label": {
                "id_action": "029",
                "description": "Turns off the soldering iron via the tower switch"
            }
        },
        {
            "clip_id": "81_79",
            "action_time": [
                1009.813,
                1052.247
            ],
            "action_label": {
                "id_action": "007",
                "description": "Fixes the card to the workbench using the screwdriver"
            }
        },
        {
            "clip_id": "81_80",
            "action_time": [
                1063.5,
                1065.625
            ],
            "action_label": {
                "id_action": "008",
                "description": "Turns on the power supply via the tower switch"
            }
        },
        {
            "clip_id": "81_81",
            "action_time": [
                1070.563,
                1075.386
            ],
            "action_label": {
                "id_action": "009",
                "description": "Adjusts the power supply current knob until the green LED turns on"
            }
        },
        {
            "clip_id": "81_82",
            "action_time": [
                1075.386,
                1084.0
            ],
            "action_label": {
                "id_action": "010",
                "description": "Adjusts the power supply voltage knob setting it to 5 Volts"
            }
        },
        {
            "clip_id": "81_83",
            "action_time": [
                1089.829,
                1099.938
            ],
            "action_label": {
                "id_action": "011",
                "description": "Connects the power supply cables to the card's power points"
            }
        },
        {
            "clip_id": "81_84",
            "action_time": [
                1108.407,
                1119.0
            ],
            "action_label": {
                "id_action": "030",
                "description": "Turns on the oscilloscope via the tower switch"
            }
        },
        {
            "clip_id": "81_85",
            "action_time": [
                1119.0,
                1122.672
            ],
            "action_label": {
                "id_action": "031",
                "description": "Activates the probe channel number 2 using the blue-bordered CH2 MENU button"
            }
        },
        {
            "clip_id": "81_86",
            "action_time": [
                1127.891,
                1137.157
            ],
            "action_label": {
                "id_action": "032",
                "description": "Connects the probe ground clip to test point number 1"
            }
        },
        {
            "clip_id": "81_87",
            "action_time": [
                1137.157,
                1149.376
            ],
            "action_label": {
                "id_action": "033",
                "description": "Uses the probe tip to check some signal brought to test point number 2 on the card"
            }
        },
        {
            "clip_id": "81_88",
            "action_time": [
                1149.38,
                1153.86
            ],
            "action_label": {
                "id_action": "034",
                "description": "Presses the oscilloscope's Auto Set button"
            }
        },
        {
            "clip_id": "81_89",
            "action_time": [
                1163.516,
                1170.219
            ],
            "action_label": {
                "id_action": "035",
                "description": "Randomly rotates the position knob"
            }
        },
        {
            "clip_id": "81_90",
            "action_time": [
                1179.532,
                1185.292
            ],
            "action_label": {
                "id_action": "036",
                "description": "Uses the probe tip at test point number 3 on the card"
            }
        },
        {
            "clip_id": "81_91",
            "action_time": [
                1185.292,
                1187.36
            ],
            "action_label": {
                "id_action": "034",
                "description": "Presses the oscilloscope's Auto Set button"
            }
        },
        {
            "clip_id": "81_92",
            "action_time": [
                1198.938,
                1205.485
            ],
            "action_label": {
                "id_action": "035",
                "description": "Randomly rotates the position knob"
            }
        },
        {
            "clip_id": "81_93",
            "action_time": [
                1215.391,
                1229.688
            ],
            "action_label": {
                "id_action": "037",
                "description": "Uses the probe tip at test point number 4 on the card"
            }
        },
        {
            "clip_id": "81_94",
            "action_time": [
                1229.688,
                1232.313
            ],
            "action_label": {
                "id_action": "034",
                "description": "Presses the oscilloscope's Auto Set button"
            }
        },
        {
            "clip_id": "81_95",
            "action_time": [
                1242.157,
                1247.735
            ],
            "action_label": {
                "id_action": "035",
                "description": "Randomly rotates the position knob"
            }
        },
        {
            "clip_id": "81_96",
            "action_time": [
                1254.407,
                1261.829
            ],
            "action_label": {
                "id_action": "038",
                "description": "Uses the probe tip at test point number 5 on the card"
            }
        },
        {
            "clip_id": "81_97",
            "action_time": [
                1261.829,
                1264.141
            ],
            "action_label": {
                "id_action": "034",
                "description": "Presses the oscilloscope's Auto Set button"
            }
        },
        {
            "clip_id": "81_98",
            "action_time": [
                1274.25,
                1277.907
            ],
            "action_label": {
                "id_action": "035",
                "description": "Randomly rotates the position knob"
            }
        },
        {
            "clip_id": "81_99",
            "action_time": [
                1285.704,
                1291.657
            ],
            "action_label": {
                "id_action": "043",
                "description": "Uses the probe tip at test point number 6 on the card"
            }
        },
        {
            "clip_id": "81_100",
            "action_time": [
                1291.658,
                1294.079
            ],
            "action_label": {
                "id_action": "034",
                "description": "Presses the oscilloscope's Auto Set button"
            }
        },
        {
            "clip_id": "81_101",
            "action_time": [
                1303.75,
                1307.563
            ],
            "action_label": {
                "id_action": "035",
                "description": "Randomly rotates the position knob"
            }
        },
        {
            "clip_id": "81_102",
            "action_time": [
                1320.141,
                1322.313
            ],
            "action_label": {
                "id_action": "034",
                "description": "Presses the oscilloscope's Auto Set button"
            }
        },
        {
            "clip_id": "81_103",
            "action_time": [
                1334.391,
                1338.366
            ],
            "action_label": {
                "id_action": "035",
                "description": "Randomly rotates the position knob"
            }
        },
        {
            "clip_id": "81_104",
            "action_time": [
                1349.297,
                1351.454
            ],
            "action_label": {
                "id_action": "012",
                "description": "Turns off the card's power supply via the tower switch"
            }
        },
        {
            "clip_id": "81_105",
            "action_time": [
                1351.46,
                1359.813
            ],
            "action_label": {
                "id_action": "013",
                "description": "Resets the power supply current and voltage knobs to 0"
            }
        },
        {
            "clip_id": "81_106",
            "action_time": [
                1365.485,
                1375.485
            ],
            "action_label": {
                "id_action": "040",
                "description": "Disconnects the ground clip and oscilloscope probe"
            }
        },
        {
            "clip_id": "81_107",
            "action_time": [
                1375.485,
                1379.282
            ],
            "action_label": {
                "id_action": "014",
                "description": "Disconnects the power supply cables"
            }
        },
        {
            "clip_id": "81_108",
            "action_time": [
                1386.469,
                1390.454
            ],
            "action_label": {
                "id_action": "041",
                "description": "Deactivates the probe channel number 2"
            }
        },
        {
            "clip_id": "81_109",
            "action_time": [
                1390.462,
                1395.906
            ],
            "action_label": {
                "id_action": "042",
                "description": "Turns off the oscilloscope via the tower switch"
            }
        },
        {
            "clip_id": "81_110",
            "action_time": [
                1402.438,
                1440.601
            ],
            "action_label": {
                "id_action": "015",
                "description": "Removes the card from the workbench using the screwdriver"
            }
        },
        {
            "clip_id": "81_111",
            "action_time": [
                1445.188,
                1472.338
            ],
            "action_label": {
                "id_action": "044",
                "description": "Reinserts the screws in the work area using the screwdriver"
            }
        },
        {
            "clip_id": "81_112",
            "action_time": [
                1478.0,
                1495.766
            ],
            "action_label": {
                "id_action": "045",
                "description": "Disconnects the screwdriver battery and connects it to the battery charger"
            }
        },
        {
            "clip_id": "81_113",
            "action_time": [
                1495.766,
                1497.594
            ],
            "action_label": {
                "id_action": "046",
                "description": "Turns on the screwdriver battery charger via the tower switch"
            }
        },
        {
            "clip_id": "81_114",
            "action_time": [
                1503.625,
                1537.188
            ],
            "action_label": {
                "id_action": "047",
                "description": "Notes the test operation results in the register"
            }
        },
        {
            "clip_id": "81_115",
            "action_time": [
                1547.0,
                1549.563
            ],
            "action_label": {
                "id_action": "048",
                "description": "Presses the two red buttons on panel A"
            }
        }
    ]
}